hurst_calc/__init__.py
hurst_calc/hurst.py
hurst_calc-0.4.dist-info/METADATA
hurst_calc-0.4.dist-info/WHEEL
hurst_calc-0.4.dist-info/top_level.txt
hurst_calc-0.4.dist-info/RECORD
